certbot_pskz/__init__.py
certbot_pskz/dns.py
certbot_pskz/dns_test.py
etc/letsencrypt/pskz.ini
certbot_pskz-1.0.0.dist-info/LICENSE
certbot_pskz-1.0.0.dist-info/METADATA
certbot_pskz-1.0.0.dist-info/WHEEL
certbot_pskz-1.0.0.dist-info/entry_points.txt
certbot_pskz-1.0.0.dist-info/top_level.txt
certbot_pskz-1.0.0.dist-info/RECORD
